slope_er/__init__.py
slope_er/metric.py
slope_er-0.1.6.dist-info/LICENSE
slope_er-0.1.6.dist-info/METADATA
slope_er-0.1.6.dist-info/WHEEL
slope_er-0.1.6.dist-info/top_level.txt
slope_er-0.1.6.dist-info/RECORD
