Metadata-Version: 2.1
Name: slope_er
Version: 0.1.6
Summary: Python implementation of Slope Error Rate (SER) by Arsalan Rahman Mirza.
Author-email: Arsalan Rahman Mirza <arsalan.mirza@soran.edu.iq>
Project-URL: Homepage, https://pypi.org/project/slope_er/
Classifier: Programming Language :: Python :: 3
Classifier: License :: OSI Approved :: MIT License
Classifier: Operating System :: OS Independent
Requires-Python: >=3.8
License-File: LICENSE
